notify/__init__.py
notify/__main__.py
notify/mail.py
notify/message.py
notify/pm.py
sc_notify-1.2.0.dist-info/METADATA
sc_notify-1.2.0.dist-info/WHEEL
sc_notify-1.2.0.dist-info/entry_points.txt
sc_notify-1.2.0.dist-info/top_level.txt
sc_notify-1.2.0.dist-info/RECORD
